[
    {
      "id": "6425cd62d4e3d4fcec586036",
      "AuthorName": "Kerri Schroeder",
      "title": "We are web developer",
      "readtime": 5,
      "images": "https://cdn.pixabay.com/photo/2015/01/08/18/29/entrepreneur-593358_1280.jpg",
      "PublishDate": "Mar 3 (12 Days ago)",
      "AuthorImages": "https://images.unsplash.com/photo-1568602471122-7832951cc4c5?ixlib=rb-4.0.3&ixid=MnwxMjA3fDB8MHxwaG90by1wYWdlfHx8fGVufDB8fHx8&auto=format&fit=crop&w=870&q=80"
    },
    {
      "id": "6425cd6298bea3b594384367",
      "AuthorName": "Ferguson Hall",
      "title": "How to get your first job as a self-taught programmer",
      "readtime": 10,
      "images": "https://cdn.pixabay.com/photo/2015/01/08/18/29/entrepreneur-593358_1280.jpg",
      "PublishDate": "Mar 14 (4 Days ago)",
      "AuthorImages": "https://images.unsplash.com/photo-1568602471122-7832951cc4c5?ixlib=rb-4.0.3&ixid=MnwxMjA3fDB8MHxwaG90by1wYWdlfHx8fGVufDB8fHx8&auto=format&fit=crop&w=870&q=80"
    },
    {
      "id": "6425cd62e61af28d5566098b",
      "AuthorName": "Underwood Rogers",
      "title": "We are already leant html css javaScript",
      "readtime": 3,
      "images": "https://cdn.pixabay.com/photo/2015/01/08/18/29/entrepreneur-593358_1280.jpg",
      "PublishDate": "Mar 5 (14 Days ago)",
      "AuthorImages": "https://images.unsplash.com/photo-1568602471122-7832951cc4c5?ixlib=rb-4.0.3&ixid=MnwxMjA3fDB8MHxwaG90by1wYWdlfHx8fGVufDB8fHx8&auto=format&fit=crop&w=870&q=80"
    },
    {
      "id": "6425cd627c83d93c78f79a84",
      "AuthorName": "Gutierrez Washington",
      "title": "We Learn React",
      "readtime": 15,
      "images": "https://cdn.pixabay.com/photo/2015/01/08/18/29/entrepreneur-593358_1280.jpg",
      "PublishDate": "Mar 13 (2 Days ago)",
      "AuthorImages": "https://images.unsplash.com/photo-1568602471122-7832951cc4c5?ixlib=rb-4.0.3&ixid=MnwxMjA3fDB8MHxwaG90by1wYWdlfHx8fGVufDB8fHx8&auto=format&fit=crop&w=870&q=80"
    },
    {
      "id": "6425cd6235feaf6c448344ae",
      "AuthorName": "Michelle Bryan",
      "title": "How to get your first job as a self-taught programmer",
      "readtime": 20,
      "images": "https://cdn.pixabay.com/photo/2015/01/08/18/29/entrepreneur-593358_1280.jpg",
      "PublishDate": "Mar 18 (5 Days ago)",
      "AuthorImages": "https://images.unsplash.com/photo-1568602471122-7832951cc4c5?ixlib=rb-4.0.3&ixid=MnwxMjA3fDB8MHxwaG90by1wYWdlfHx8fGVufDB8fHx8&auto=format&fit=crop&w=870&q=80"
    },
    {
      "id": "6425cd62548753b96e3c7bb8",
      "AuthorName": "Wynn Clark",
      "title": "Future Programmer",
      "readtime": 13,
      "images": "https://cdn.pixabay.com/photo/2015/01/08/18/29/entrepreneur-593358_1280.jpg",
      "PublishDate": "Mar 14 (4 Days ago)",
      "AuthorImages": "https://images.unsplash.com/photo-1568602471122-7832951cc4c5?ixlib=rb-4.0.3&ixid=MnwxMjA3fDB8MHxwaG90by1wYWdlfHx8fGVufDB8fHx8&auto=format&fit=crop&w=870&q=80"
    }
]